<?xml version="1.0"?>
<opencv_storage>
<stage8>
  <maxWeakCount>29</maxWeakCount>
  <stageThreshold>-1.6289700269699097e+00</stageThreshold>
  <weakClassifiers>
    <_>
      <internalNodes>
        0 -1 13377 7.7621405944228172e-03</internalNodes>
      <leafValues>
        -6.4990162849426270e-01 9.2198580503463745e-02</leafValues></_>
    <_>
      <internalNodes>
        0 -1 213851 -8.9116604067385197e-04</internalNodes>
      <leafValues>
        -6.1545538902282715e-01 -1.4186422340571880e-02</leafValues></_>
    <_>
      <internalNodes>
        0 -1 91532 2.0805264357477427e-03</internalNodes>
      <leafValues>
        5.6537710130214691e-02 -6.7953026294708252e-01</leafValues></_>
    <_>
      <internalNodes>
        0 -1 810323 -1.1014327174052596e-04</internalNodes>
      <leafValues>
        -4.3534412980079651e-01 1.1676729470491409e-01</leafValues></_>
    <_>
      <internalNodes>
        0 -1 709228 -1.9931364804506302e-03</internalNodes>
      <leafValues>
        -4.8292919993400574e-01 5.9763584285974503e-02</leafValues></_>
    <_>
      <internalNodes>
        0 -1 761631 2.3144549049902707e-04</internalNodes>
      <leafValues>
        1.6004943847656250e-01 -3.4184220433235168e-01</leafValues></_>
    <_>
      <internalNodes>
        0 -1 9329 -3.0041148420423269e-03</internalNodes>
      <leafValues>
        3.4937426447868347e-01 -1.1707876622676849e-01</leafValues></_>
    <_>
      <internalNodes>
        0 -1 809842 -1.0847446974366903e-03</internalNodes>
      <leafValues>
        4.3634513020515442e-01 -8.2978904247283936e-02</leafValues></_>
    <_>
      <internalNodes>
        0 -1 277208 -7.7945934608578682e-03</internalNodes>
      <leafValues>
        -5.6305480003356934e-01 7.4147291481494904e-02</leafValues></_>
    <_>
      <internalNodes>
        0 -1 639971 -4.0068253874778748e-03</internalNodes>
      <leafValues>
        2.5229379534721375e-01 -1.4021944999694824e-01</leafValues></_>
    <_>
      <internalNodes>
        0 -1 68560 -8.5789710283279419e-03</internalNodes>
      <leafValues>
        4.2090359330177307e-01 -8.8452495634555817e-02</leafValues></_>
    <_>
      <internalNodes>
        0 -1 330863 1.7374234739691019e-03</internalNodes>
      <leafValues>
        -1.2833015620708466e-01 3.0849438905715942e-01</leafValues></_>
    <_>
      <internalNodes>
        0 -1 2464 1.6683156136423349e-03</internalNodes>
      <leafValues>
        8.0652430653572083e-02 -4.8493489623069763e-01</leafValues></_>
    <_>
      <internalNodes>
        0 -1 673344 -7.2944620624184608e-03</internalNodes>
      <leafValues>
        3.1093940138816833e-01 -1.2685012817382813e-01</leafValues></_>
    <_>
      <internalNodes>
        0 -1 713167 -4.8758037155494094e-04</internalNodes>
      <leafValues>
        -6.3923150300979614e-01 6.1841614544391632e-02</leafValues></_>
    <_>
      <internalNodes>
        0 -1 811440 3.1854948028922081e-03</internalNodes>
      <leafValues>
        -8.8933184742927551e-02 4.7491538524627686e-01</leafValues></_>
    <_>
      <internalNodes>
        0 -1 809471 -3.9252783171832561e-03</internalNodes>
      <leafValues>
        3.7844830751419067e-01 -1.1392381042242050e-01</leafValues></_>
    <_>
      <internalNodes>
        0 -1 405498 4.9372948706150055e-03</internalNodes>
      <leafValues>
        -1.5379016101360321e-01 2.7456659078598022e-01</leafValues></_>
    <_>
      <internalNodes>
        0 -1 813025 -1.3894512085244060e-04</internalNodes>
      <leafValues>
        -3.8609862327575684e-01 1.1191301792860031e-01</leafValues></_>
    <_>
      <internalNodes>
        0 -1 812173 -2.6882947422564030e-03</internalNodes>
      <leafValues>
        -5.1081234216690063e-01 6.9806598126888275e-02</leafValues></_>
    <_>
      <internalNodes>
        0 -1 809482 3.2078754156827927e-04</internalNodes>
      <leafValues>
        9.5072716474533081e-02 -4.5045235753059387e-01</leafValues></_>
    <_>
      <internalNodes>
        0 -1 538969 -6.9502554833889008e-04</internalNodes>
      <leafValues>
        -5.8538860082626343e-01 5.7640619575977325e-02</leafValues></_>
    <_>
      <internalNodes>
        0 -1 751707 7.0057162083685398e-03</internalNodes>
      <leafValues>
        -1.1125781387090683e-01 3.6328354477882385e-01</leafValues></_>
    <_>
      <internalNodes>
        0 -1 156704 2.8279144316911697e-04</internalNodes>
      <leafValues>
        8.0090619623661041e-02 -4.0951916575431824e-01</leafValues></_>
    <_>
      <internalNodes>
        0 -1 121843 -9.7864232957363129e-03</internalNodes>
      <leafValues>
        2.9327064752578735e-01 -1.1148535460233688e-01</leafValues></_>
    <_>
      <internalNodes>
        0 -1 82911 -6.6050202585756779e-03</internalNodes>
      <leafValues>
        2.6469224691390991e-01 -1.3505636155605316e-01</leafValues></_>
    <_>
      <internalNodes>
        0 -1 276017 -1.7141348216682673e-03</internalNodes>
      <leafValues>
        2.6274758577346802e-01 -1.3461889326572418e-01</leafValues></_>
    <_>
      <internalNodes>
        0 -1 815820 -1.5300200320780277e-03</internalNodes>
      <leafValues>
        -3.4174028038978577e-01 1.1486796289682388e-01</leafValues></_>
    <_>
      <internalNodes>
        0 -1 431580 -5.4484996944665909e-03</internalNodes>
      <leafValues>
        -7.3904508352279663e-01 4.2167823761701584e-02</leafValues></_></weakClassifiers></stage8>
</opencv_storage>
