<?xml version="1.0"?>
<opencv_storage>
<stage11>
  <maxWeakCount>28</maxWeakCount>
  <stageThreshold>-1.1490765810012817e+00</stageThreshold>
  <weakClassifiers>
    <_>
      <internalNodes>
        0 -1 9391 -77 -1563706433 -1379961872 601858490 -22812 44020976
        -252185536 1365243287</internalNodes>
      <leafValues>
        1.2414605170488358e-01 7.0573824644088745e-01</leafValues></_>
    <_>
      <internalNodes>
        0 -1 5668 -281809297 -134844449 -421539986 -323159556
        -1208484354 -13349 -1130748 -134742066</internalNodes>
      <leafValues>
        -2.5511598587036133e-01 4.2467924952507019e-01</leafValues></_>
    <_>
      <internalNodes>
        0 -1 451 -673185829 -85987961 -219491616 -220005634 -168859785
        1163032326 -75566302 -144179225</internalNodes>
      <leafValues>
        -2.3757928609848022e-01 4.5447996258735657e-01</leafValues></_>
    <_>
      <internalNodes>
        0 -1 6152 134744701 462635096 37992447 264049117 -1617294642
        -537977848 -1682129989 -1097330948</internalNodes>
      <leafValues>
        -3.5179394483566284e-01 3.0931326746940613e-01</leafValues></_>
    <_>
      <internalNodes>
        0 -1 7541 1448068645 1400357137 -1572297484 544223995 1924391679
        -1234996792 -1292897924 -1325687809</internalNodes>
      <leafValues>
        -3.9130109548568726e-01 2.3834727704524994e-01</leafValues></_>
    <_>
      <internalNodes>
        0 -1 8306 -137896082 -715458082 -146710838 -766641590
        -1876561475 273859037 144300953 490207551</internalNodes>
      <leafValues>
        -3.6719202995300293e-01 2.4908354878425598e-01</leafValues></_>
    <_>
      <internalNodes>
        0 -1 5765 1574442239 991063774 -657253927 473831677 1556659966
        -12408497 -1081586925 -1413988867</internalNodes>
      <leafValues>
        -2.8302103281021118e-01 3.1190395355224609e-01</leafValues></_>
    <_>
      <internalNodes>
        0 -1 8 -393228827 -912394265 -637724673 -168297049 -2139892299
        -1963466761 -821594625 -168336425</internalNodes>
      <leafValues>
        -2.1522477269172668e-01 3.9667025208473206e-01</leafValues></_>
    <_>
      <internalNodes>
        0 -1 9399 -402653321 197902040 73076840 422443206 -1243942760
        260766314 1170036957 1239937455</internalNodes>
      <leafValues>
        -2.9818156361579895e-01 3.0341568589210510e-01</leafValues></_>
    <_>
      <internalNodes>
        0 -1 6853 141037605 -18349892 -1018095777 1069781025 -58524705
        -1143554022 -773931495 -1626533827</internalNodes>
      <leafValues>
        -3.2796898484230042e-01 2.6520961523056030e-01</leafValues></_>
    <_>
      <internalNodes>
        0 -1 5255 1646736722 -183960636 424107506 300606902 -1428969039
        -1847360907 -1665223504 -2131247905</internalNodes>
      <leafValues>
        -3.3387416601181030e-01 2.5576049089431763e-01</leafValues></_>
    <_>
      <internalNodes>
        0 -1 396 -824743286 -492224367 1559481410 773312578 1159494454
        1903636529 563828224 1970526067</internalNodes>
      <leafValues>
        -5.7124060392379761e-01 1.3641339540481567e-01</leafValues></_>
    <_>
      <internalNodes>
        0 -1 8546 -1067517828 -1970502528 -1239837964 427095544
        -1605702740 -2007056252 93971672 252705964</internalNodes>
      <leafValues>
        -3.8455387949943542e-01 2.1355447173118591e-01</leafValues></_>
    <_>
      <internalNodes>
        0 -1 9207 -706748585 445215594 -1696605022 273561842 -465100698
        9541958 1907851840 -1862279178</internalNodes>
      <leafValues>
        -3.7619596719741821e-01 2.1995832026004791e-01</leafValues></_>
    <_>
      <internalNodes>
        0 -1 3074 -1478859536 1969580149 297951102 230334711 -2013025859
        -2137154725 -1711145735 1055215629</internalNodes>
      <leafValues>
        -3.4849944710731506e-01 2.2694145143032074e-01</leafValues></_>
    <_>
      <internalNodes>
        0 -1 1859 -96994074 -511765854 -1237229994 278919991 -935331482
        713805927 -90705079 434624243</internalNodes>
      <leafValues>
        -3.4362292289733887e-01 2.3979188501834869e-01</leafValues></_>
    <_>
      <internalNodes>
        0 -1 6630 142609648 -51757028 1410234843 1251940544 -1182208019
        -108871969 724750580 847256809</internalNodes>
      <leafValues>
        -4.6621391177177429e-01 1.8256400525569916e-01</leafValues></_>
    <_>
      <internalNodes>
        0 -1 333 -496357558 887014359 938216 435814602 -494877179
        225921749 1690632885 2031112821</internalNodes>
      <leafValues>
        -4.6008086204528809e-01 1.7245653271675110e-01</leafValues></_>
    <_>
      <internalNodes>
        0 -1 9126 -881142149 547797286 -1211706603 144961875 -21047054
        -1966617904 -780601888 -2139424161</internalNodes>
      <leafValues>
        -3.0745744705200195e-01 2.7259519696235657e-01</leafValues></_>
    <_>
      <internalNodes>
        0 -1 5883 -1065683644 -1875383995 -252767906 539630172
        -2045179618 -726104448 -518151754 34015928</internalNodes>
      <leafValues>
        -4.7519108653068542e-01 1.7064593732357025e-01</leafValues></_>
    <_>
      <internalNodes>
        0 -1 272 -19660849 -688925053 -278103540 -277434838 1868641419
        1075025163 1145549191 -134742281</internalNodes>
      <leafValues>
        -1.7797179520130157e-01 4.8151785135269165e-01</leafValues></_>
    <_>
      <internalNodes>
        0 -1 8891 -715731560 232160629 -1898342815 83713349 541204476
        24019089 404231421 139443577</internalNodes>
      <leafValues>
        -4.1678482294082642e-01 2.0025013387203217e-01</leafValues></_>
    <_>
      <internalNodes>
        0 -1 613 -491545054 1941531953 -1191248419 1538519027
        -1173574983 -14853840 -2071629846 1522803719</internalNodes>
      <leafValues>
        -2.7137604355812073e-01 3.0760428309440613e-01</leafValues></_>
    <_>
      <internalNodes>
        0 -1 6646 -536543189 -772326636 -1350426756 72356415 -1666610383
        -21405684 -500179404 -2111882792</internalNodes>
      <leafValues>
        -3.2634261250495911e-01 2.5766444206237793e-01</leafValues></_>
    <_>
      <internalNodes>
        0 -1 455 2135549359 -701354597 -1384468838 -953008209 1659707327
        -50056135 2123833327 2135125551</internalNodes>
      <leafValues>
        -2.6376274228096008e-01 3.2389664649963379e-01</leafValues></_>
    <_>
      <internalNodes>
        0 -1 8158 -2147465131 643436693 -570165956 456724508 -10749218
        -678827074 -268944455 -2009588469</internalNodes>
      <leafValues>
        -3.2409560680389404e-01 2.5458681583404541e-01</leafValues></_>
    <_>
      <internalNodes>
        0 -1 9142 994224436 892907836 -150318932 -424710241 1712233688
        -1413240190 822381710 349035230</internalNodes>
      <leafValues>
        -3.9570951461791992e-01 2.0905929803848267e-01</leafValues></_>
    <_>
      <internalNodes>
        0 -1 9383 -234891025 -528939572 502166084 1347225830 -5818410
        98497900 -31277318 -762588421</internalNodes>
      <leafValues>
        -2.3257811367511749e-01 3.6022588610649109e-01</leafValues></_></weakClassifiers></stage11>
</opencv_storage>
